peoplefinder/GetData.py
peoplefinder/GetPhoto.py
peoplefinder/Main.py
peoplefinder/SaveData.py
peoplefinder/TelegramUpload.py
peoplefinder/__init__.py
peoplefinder-1.0b1.data/scripts/peoplefinder
peoplefinder-1.0b1.data/scripts/peopleuploader
peoplefinder-1.0b1.dist-info/LICENSE
peoplefinder-1.0b1.dist-info/METADATA
peoplefinder-1.0b1.dist-info/WHEEL
peoplefinder-1.0b1.dist-info/top_level.txt
peoplefinder-1.0b1.dist-info/RECORD
