Metadata-Version: 2.1
Name: peoplefinder
Version: 1.0b1
Summary: Tools for finding and storing profile pics of whatsapp contacts in large scale.
Home-page: https://github.com/fmndantas/people-finder
Author: Eduardo Nunes & Fernando Dantas
License: MIT
Platform: UNKNOWN
Classifier: Programming Language :: Python :: 3
Classifier: License :: OSI Approved :: MIT License
Classifier: Operating System :: Unix
Requires-Dist: numpy (>=1.11)
Requires-Dist: selenium
Requires-Dist: tqdm
Requires-Dist: python-telegram-bot
Requires-Dist: astropy
